{
  "$schema": "https://developer.microsoft.com/json-schemas/fabric/item/report/definition/visualContainer/2.10.0/schema.json",
  "name": "21096ac47a94455e9886",
  "position": {
    "x": 640.09975062344142,
    "y": 70.922693266832908,
    "z": 2000,
    "height": 124.78802992518703,
    "width": 311.52119700748131,
    "tabOrder": 2000
  },
  "visual": {
    "visualType": "htmlContent443BE3AD55E043BF878BED274D3A6855",
    "query": {
      "queryState": {
        "content": {
          "projections": [
            {
              "field": {
                "Measure": {
                  "Expression": {
                    "SourceRef": {
                      "Entity": "formulas"
                    }
                  },
                  "Property": "VIS _HTML Card Active Listening Days"
                }
              },
              "queryRef": "formulas.VIS _HTML Card Active Listening Days",
              "nativeQueryRef": "VIS _HTML Card Active Listening Days"
            }
          ]
        }
      },
      "sortDefinition": {
        "isDefaultSort": true
      }
    },
    "visualContainerObjects": {
      "background": [
        {
          "properties": {
            "show": {
              "expr": {
                "Literal": {
                  "Value": "false"
                }
              }
            }
          }
        }
      ],
      "title": [
        {
          "properties": {
            "show": {
              "expr": {
                "Literal": {
                  "Value": "false"
                }
              }
            }
          }
        }
      ],
      "visualHeader": [
        {
          "properties": {
            "show": {
              "expr": {
                "Literal": {
                  "Value": "false"
                }
              }
            }
          }
        }
      ],
      "visualTooltip": [
        {
          "properties": {
            "show": {
              "expr": {
                "Literal": {
                  "Value": "false"
                }
              }
            }
          }
        }
      ],
      "border": [
        {
          "properties": {
            "show": {
              "expr": {
                "Literal": {
                  "Value": "false"
                }
              }
            }
          }
        }
      ]
    },
    "drillFilterOtherVisuals": true
  }
}